LICENSE
README.md
http_copy.py
setup.py
http_copy.egg-info/PKG-INFO
http_copy.egg-info/SOURCES.txt
http_copy.egg-info/dependency_links.txt
http_copy.egg-info/entry_points.txt
http_copy.egg-info/requires.txt
http_copy.egg-info/top_level.txt